lightroom_export_organizer/__init__.py
lightroom_export_organizer/greet_world.py
lightroom_export_organizer/org_folders.py
lightroom_export_organizer/version.py
lightroom_export_organizer/tools/__init__.py
lightroom_export_organizer/tools/hello_world.py
lightroom_export_organizer/tools/org_folders.py
lightroom_export_organizer-0.12.data/data/share/lightroom_export_organizer/README.rst
lightroom_export_organizer-0.12.dist-info/METADATA
lightroom_export_organizer-0.12.dist-info/RECORD
lightroom_export_organizer-0.12.dist-info/WHEEL
lightroom_export_organizer-0.12.dist-info/entry_points.txt
lightroom_export_organizer-0.12.dist-info/top_level.txt
