Metadata-Version: 2.1
Name: lightroom-export-organizer
Version: 0.12
Summary: TODO
Home-page: https://github.com/aagnone3/lightroom-export-organizer
Author: Anthony Agnone
Author-email: anthonyagnone@gmail.com
License: UNKNOWN
Platform: UNKNOWN
Classifier: Development Status :: 3 - Alpha
Classifier: Programming Language :: Python :: 3
Classifier: Topic :: Scientific/Engineering
Requires-Dist: pandas
Requires-Dist: numpy
Requires-Dist: structlog
Requires-Dist: PyQt5
